grammaropt/__init__.py
grammaropt/grammar.py
grammaropt/random.py
grammaropt/rnn.py
grammaropt/terminal_types.py
grammaropt-0.1.3.dist-info/DESCRIPTION.rst
grammaropt-0.1.3.dist-info/METADATA
grammaropt-0.1.3.dist-info/RECORD
grammaropt-0.1.3.dist-info/WHEEL
grammaropt-0.1.3.dist-info/metadata.json
grammaropt-0.1.3.dist-info/top_level.txt
