Metadata-Version: 2.0
Name: grammaropt
Version: 0.1.3
Summary: UNKNOWN
Home-page: UNKNOWN
Author: mehdi cherti
Author-email: mehdicherti@gmail.com
License: MIT
Platform: any
Classifier: Intended Audience :: Science/Research
Classifier: Intended Audience :: Developers
Classifier: License :: OSI Approved
Classifier: Programming Language :: Python
Classifier: Topic :: Software Development
Classifier: Topic :: Scientific/Engineering
Classifier: Operating System :: Microsoft :: Windows
Classifier: Operating System :: POSIX
Classifier: Operating System :: Unix
Classifier: Operating System :: MacOS
Requires: parsimonious
Requires: numpy
Requires-Dist: numpy
Requires-Dist: parsimonious
